dotmoshez/__init__.py
dotmoshez/__main__.py
dotmoshez/bash.py
dotmoshez/clean_ipynb.py
dotmoshez/git_extras.py
dotmoshez/init_py.py
dotmoshez/ssh.py
dotmoshez/tests/__init__.py
dotmoshez/tests/test_init.py
dotmoshez-2024.1.22.64939.dist-info/METADATA
dotmoshez-2024.1.22.64939.dist-info/WHEEL
dotmoshez-2024.1.22.64939.dist-info/entry_points.txt
dotmoshez-2024.1.22.64939.dist-info/top_level.txt
dotmoshez-2024.1.22.64939.dist-info/RECORD
