Metadata-Version: 2.1
Name: dotmoshez
Version: 2024.1.22.64939
Summary: Moshe'z personal utilities
Author-email: Moshe Zadka <moshez@zadka.club>
License: Permission is hereby granted, free of charge, to any person obtaining a
Project-URL: Homepage, https://github.com/moshez/dotmoshez
Requires-Dist: gather
Requires-Dist: virtualenvwrapper
Requires-Dist: hyperlink
Requires-Dist: copier
Requires-Dist: commander-data
Requires-Dist: pipx
Provides-Extra: docs
Requires-Dist: sphinx ; extra == 'docs'
Provides-Extra: lint
Requires-Dist: flake8 ; extra == 'lint'
Requires-Dist: black ; extra == 'lint'
Provides-Extra: mypy
Requires-Dist: mypy ; extra == 'mypy'
Provides-Extra: tests
Requires-Dist: virtue ; extra == 'tests'
Requires-Dist: pyhamcrest ; extra == 'tests'
Requires-Dist: coverage ; extra == 'tests'
